spacedork/__init__.py
spacedork/cli.py
spacedork/reps/__init__.py
spacedork/reps/base.py
spacedork/reps/fofa.py
spacedork/reps/zoomeye.py
spacedork-3.3.9.dist-info/METADATA
spacedork-3.3.9.dist-info/WHEEL
spacedork-3.3.9.dist-info/entry_points.txt
spacedork-3.3.9.dist-info/top_level.txt
spacedork-3.3.9.dist-info/RECORD
