Metadata-Version: 2.1
Name: spacedork
Version: 3.3.9
Home-page: 
Author: 
Author-email: tongchengbin@outlook.com
Maintainer: 
Keywords: dork search
Platform: any
Requires-Python: >=3.6
Requires-Dist: PyYAML
